pipeflow/__init__.py
pipeflow/error.py
pipeflow/log.py
pipeflow/server.py
pipeflow/tasks.py
pipeflow/endpoints/__init__.py
pipeflow/endpoints/endpoints.py
pipeflow/endpoints/http_endpoints.py
pipeflow/endpoints/nsq_endpoints.py
pipeflow/endpoints/rabbitmq_endpoints.py
pipeflow/endpoints/redis_endpoints.py
pypipeflow-1.0.1.dist-info/LICENSE
pypipeflow-1.0.1.dist-info/METADATA
pypipeflow-1.0.1.dist-info/WHEEL
pypipeflow-1.0.1.dist-info/top_level.txt
pypipeflow-1.0.1.dist-info/RECORD
