Metadata-Version: 2.1
Name: pypipeflow
Version: 1.0.1
Summary: a simple library that you can set up service based on different kinds of MQ
Home-page: https://github.com/everAwayne/pipeflow
Author: Awayne
Author-email: everAwayne@gmail.com
License: UNKNOWN
Platform: UNKNOWN
Classifier: Framework :: AsyncIO
Classifier: Development Status :: 5 - Production/Stable
Classifier: Intended Audience :: Developers
Classifier: Natural Language :: English
Classifier: License :: OSI Approved :: Apache Software License
Classifier: Programming Language :: Python
Classifier: Programming Language :: Python :: 3 :: Only
Classifier: Programming Language :: Python :: 3.5
Classifier: Programming Language :: Python :: 3.6
Classifier: Programming Language :: Python :: 3.7
Classifier: Programming Language :: Python :: Implementation :: CPython
Classifier: Programming Language :: Python :: Implementation :: PyPy
Requires-Python: >=3.5
Requires-Dist: aiohttp
Requires-Dist: pynsq (>=0.9.0)
Requires-Dist: redis
Requires-Dist: aio-pika
Provides-Extra: uvloop
Requires-Dist: uvloop ; extra == 'uvloop'
